mlaas/__init__.py
mlaas/pkg/__init__.py
mlaas/pkg/services/__init__.py
mlaas/pkg/services/image_background_removal/__init__.py
mlaas/pkg/services/image_background_removal/end_point.py
mlaas/pkg/services/speech2text/__init__.py
mlaas/pkg/services/speech2text/end_point.py
mlaas/pkg/services/text2speech/__init__.py
mlaas/pkg/services/text2speech/end_point.py
mlaas/pkg/services/translation/__init__.py
mlaas/pkg/services/translation/end_point.py
mlaas/services/__init__.py
mlaas/services/image_background_removal.py
mlaas/services/speech2text.py
mlaas/services/text2speech.py
mlaas/services/translation.py
pkg/__init__.py
src/__init__.py
src/pkg/__init__.py
mlaas-0.0.11.dist-info/LICENSE
mlaas-0.0.11.dist-info/METADATA
mlaas-0.0.11.dist-info/WHEEL
mlaas-0.0.11.dist-info/top_level.txt
mlaas-0.0.11.dist-info/RECORD
